LICENSE
README.md
setup.py
rewise/__init__.py
rewise/rewise.py
rewise.egg-info/PKG-INFO
rewise.egg-info/SOURCES.txt
rewise.egg-info/dependency_links.txt
rewise.egg-info/top_level.txt