Metadata-Version: 2.4
Name: rewise
Version: 0.1.0
Summary: Google auto-complete wrapper
Home-page: https://github.com/s0md3v/rewise
Download-URL: https://github.com/s0md3v/rewise/archive/v0.1.0.zip
Author: Somdev Sangwan
Author-email: s0md3v@gmail.com
License: MIT License
Keywords: google,spell,spell-check,autocorrect,autocomplete
Classifier: Development Status :: 5 - Production/Stable
Classifier: Intended Audience :: Developers
Classifier: Operating System :: OS Independent
Classifier: Topic :: Text Processing
Classifier: License :: OSI Approved :: MIT License
Classifier: Programming Language :: Python
License-File: LICENSE
Dynamic: author
Dynamic: author-email
Dynamic: classifier
Dynamic: description
Dynamic: description-content-type
Dynamic: download-url
Dynamic: home-page
Dynamic: keywords
Dynamic: license
Dynamic: license-file
Dynamic: summary
